hfs_module/__init__.py
hfs_module-9.9.9.dist-info/METADATA
hfs_module-9.9.9.dist-info/WHEEL
hfs_module-9.9.9.dist-info/top_level.txt
hfs_module-9.9.9.dist-info/RECORD
