Metadata-Version: 2.4
Name: hfs_module
Version: 9.9.9
Summary: PoC for Dependency Confusion Vulnerability
